powerups/__init__.py
powerups/df_utils.py
mushroom_kingdom-0.1.2.dist-info/LICENSE
mushroom_kingdom-0.1.2.dist-info/METADATA
mushroom_kingdom-0.1.2.dist-info/WHEEL
mushroom_kingdom-0.1.2.dist-info/top_level.txt
mushroom_kingdom-0.1.2.dist-info/RECORD
