Metadata-Version: 2.1
Name: mushroom-kingdom
Version: 0.1.2
Summary: a collection of data science helper functions
Home-page: https://github.com/xander-bennett/mushroom-kingdom
Author: xander-bennett
License: UNKNOWN
Platform: UNKNOWN
Classifier: Programming Language :: Python :: 3
Classifier: License :: OSI Approved :: MIT License
Classifier: Operating System :: OS Independent
Requires-Python: >=3.5
Requires-Dist: numpy
Requires-Dist: pandas
